LICENSE
README.rst
setup.py
cs/__init__.py
cs.togglecanonical.egg-info/PKG-INFO
cs.togglecanonical.egg-info/SOURCES.txt
cs.togglecanonical.egg-info/dependency_links.txt
cs.togglecanonical.egg-info/entry_points.txt
cs.togglecanonical.egg-info/namespace_packages.txt
cs.togglecanonical.egg-info/not-zip-safe
cs.togglecanonical.egg-info/requires.txt
cs.togglecanonical.egg-info/top_level.txt
cs/togglecanonical/__init__.py
cs/togglecanonical/configure.zcml
cs/togglecanonical/tests.py
cs/togglecanonical/upgrades.py
cs/togglecanonical/profiles/default/actions.xml
cs/togglecanonical/profiles/default/metadata.xml
docs/HISTORY.txt
docs/INSTALL.txt
docs/LICENSE.GPL
docs/LICENSE.txt