Metadata-Version: 1.1
Name: cs.togglecanonical
Version: 1.1
Summary: Hide and show canonical language fields in Plone edit form
Home-page: https://github.com/codesyntax/cs.togglecanonical
Author: Mikel Larreategi
Author-email: mlarreategi@codesyntax.com
License: GPL
Platform: UNKNOWN
Classifier: Framework :: Plone
Classifier: Programming Language :: Python
Classifier: Topic :: Software Development :: Libraries :: Python Modules
